{
  "briefName": 	"capitals",
  "title":      "Americas Capitals Quiz",
  "config": {
    "randomizeQuestionSequence": true,
    "autoSubmit": true
  },
  "questions": [
    {
      "id":      0,
      "question": "What is the capital of Paraguay?",
      "pictureQuestion":  "images/asuncion.jpg",
      "type":     "pictureQuestionShortAnswer",
      "correctAnswerArray": [
        "Asuncion",
	"Asunción"
      ]
	    },
     {
      "id":      1,
      "question": "What is the capital of Costa Rica?",
      "pictureQuestion":  "images/sanjose.jpg",
      "type":     "pictureQuestionShortAnswer",
      "correctAnswerArray": [
        "San José",
	"San Jose"
      ]
	    },
     {
      "id":      2,
      "question": "What is the capital of Venezuela?",
      "pictureQuestion":  "images/caracas.jpeg",
      "type":     "pictureQuestionShortAnswer",
      "correctAnswerArray": [
        "Caracas"
      ]
	    },
     {
      "id":      3,
      "question": "What is the capital of Honduras?",
      "pictureQuestion":  "images/tegucigalpa.jpg",
      "type":     "pictureQuestionShortAnswer",
      "correctAnswerArray": [
        "Tegucigalpa"
      ]
	    },
     {
      "id":      4,
      "question": "What is the capital of Uruguay?",
      "pictureQuestion":  "images/montevideo.jpg",
      "type":     "pictureQuestionShortAnswer",
      "correctAnswerArray": [
        "Montevideo"
      ]
	    },
     {
      "id":      5,
      "question": "What is the capital of Suriname?",
      "pictureQuestion":  "images/paramaribo.jpg",
      "type":     "pictureQuestionShortAnswer",
      "correctAnswerArray": [
        "Paramaribo"
      ]
	    },
     {
      "id":      6,
      "question": "What is the capital of Nicaragua?",
      "pictureQuestion":  "images/managua.jpg",
      "type":     "pictureQuestionShortAnswer",
      "correctAnswerArray": [
        "Managua"
      ]
	    },
     {
      "id":      7,
      "question": "What is the capital of Cuba?",
      "pictureQuestion":  "images/havana.jpg",
      "type":     "pictureQuestionShortAnswer",
      "correctAnswerArray": [
        "Havana"
      ]
	    },
	 {
      "id":      8,
      "question": "What is the capital of Jamaica?",
      "pictureQuestion":  "images/kingston.jpg",
      "type":     "pictureQuestionShortAnswer",
      "correctAnswerArray": [
        "Kingston"
      ]
	    },
     {
      "id":      9,
      "question": "What is the capital of Guyana?",
      "pictureQuestion":  "images/georgetown.jpg",
      "type":     "pictureQuestionShortAnswer",
      "correctAnswerArray": [
        "Georgetown"
      ]
	    }
  ]
}
